dnora_metno/__init__.py
dnora_metno/fimex_functions.py
dnora_metno/current/__init__.py
dnora_metno/current/current_readers.py
dnora_metno/ice/__init__.py
dnora_metno/ice/ice_readers.py
dnora_metno/modelrun/__init__.py
dnora_metno/modelrun/templates.py
dnora_metno/spectra/__init__.py
dnora_metno/spectra/spectral_readers.py
dnora_metno/waveseries/__init__.py
dnora_metno/waveseries/waveseries_readers.py
dnora_metno/wind/__init__.py
dnora_metno/wind/wind_readers.py
dnora_metno-0.1.0.dist-info/licenses/LICENSE
dnora_metno-0.1.0.dist-info/METADATA
dnora_metno-0.1.0.dist-info/WHEEL
dnora_metno-0.1.0.dist-info/top_level.txt
dnora_metno-0.1.0.dist-info/RECORD
