Metadata-Version: 2.4
Name: dnora-metno
Version: 0.1.0
Summary: Add-on to dnora: Access to MET Norway's weather products
Author-email: Konstantinos Christakos <konstantinosc@met.no>, Jan-Victor Björkqvist <janvb@met.no>
License: MIT License
Project-URL: homepage, https://github.com/MET-OM/dnora-metno
Project-URL: download, https://github.com/MET-OM/dnora-metno
Requires-Python: <3.11,>=3.9
License-File: LICENSE
Requires-Dist: numpy>=1.17
Requires-Dist: dnora>=2.0.4
Provides-Extra: test
Requires-Dist: pytest>=7.0; extra == "test"
Dynamic: license-file
